{
  "name": "NukiBleEsp32",
  "version": "2.0.1",
  "description": "Control Nuki smartlock via BLE from esp32 (cf762e7)",
  "keywords": "nuki ble esp32",
  "authors": [
    {
      "name": "Jeroen van de Vorst",
      "maintainer": true
    },
    {
      "name": "Bas Schouten"
    }
  ],
  "repository": {
    "type": "git",
    "url": "https://github.com/iranl/NukiBleEsp32/tree/cf762e7dbd6ed501e9b719a7a4b9590ec85c7f99"
  },
  "frameworks": "Arduino",
  "platforms": [
    "espressif32"
  ],
  "build": {
    "flags": "-Wno-unused-function"
  },
  "dependencies": [
    {
      "name": "NimBLE-Arduino",
      "version": "h2zero/NimBLE-Arduino @ ^1.4.0"
    },
    {
      "name": "CRC16",
      "version": "https://github.com/vinmenn/Crc16"
    },
    {
      "name": "BleScanner",
      "version": "https://github.com/I-Connect/BleScanner"
    }
  ]
}